LICENSE
README.md
setup.py
ccode/__init__.py
ccode.egg-info/PKG-INFO
ccode.egg-info/SOURCES.txt
ccode.egg-info/dependency_links.txt
ccode.egg-info/requires.txt
ccode.egg-info/top_level.txt