Metadata-Version: 2.1
Name: ccode
Version: 0.0.5
Summary: A library that encodes and runs any script that has been encrypted through the library in order to preserve the confidentiality of the code and preserve it from theft and preserve the programming rights of the programmer. The Lib99 library is a library that specializes in encryption and uses several offices inside it and uses a special type of encryption that was programmed in 2023 month The third on the 13th
Author: Mohammed Hamza
Author-email: eibdhhs0@gmail.com
Classifier: Operating System :: OS Independent
Classifier: Natural Language :: Arabic
Classifier: Programming Language :: Python :: 3
Classifier: License :: OSI Approved :: MIT License 
License-File: LICENSE
